maze/__init__.py
maze/cli/__init__.py
maze/cli/cli.py
maze/client/__init__.py
maze/client/front/__init__.py
maze/client/front/client.py
maze/client/front/decorator.py
maze/client/front/file_utils.py
maze/client/front/server_workflow.py
maze/client/front/task.py
maze/client/front/workflow.py
maze/client/front/builtin/__init__.py
maze/client/front/builtin/fileTask.py
maze/client/front/builtin/healthTask.py
maze/client/front/builtin/simpleTask.py
maze/client/langgraph/__init__.py
maze/client/langgraph/client.py
maze/client/maze/__init__.py
maze/client/maze/client.py
maze/client/maze/decorator.py
maze/client/maze/models.py
maze/client/maze/workflow.py
maze/client/maze/builtin/simpleTask.py
maze/config/logging_config.py
maze/core/__init__.py
maze/core/server.py
maze/core/path/__init__.py
maze/core/path/path.py
maze/core/scheduler/__init__.py
maze/core/scheduler/resource.py
maze/core/scheduler/runner.py
maze/core/scheduler/runtime.py
maze/core/scheduler/scheduler.py
maze/core/worker/__init__.py
maze/core/worker/worker.py
maze/core/workflow/__init__.py
maze/core/workflow/task.py
maze/core/workflow/workflow.py
maze/tool/__init__.py
maze/tool/csv_reader.py
maze/tool/doc_reader.py
maze/tool/figure_reader.py
maze/tool/mp3_reader.py
maze/tool/pdf_reader.py
maze/tool/search.py
maze/tool/text_reader.py
maze/tool/video_reader.py
maze/tool/weather.py
maze/tool/xlsx_reader.py
maze/utils/__init__.py
maze/utils/utils.py
maze_agent-1.0.2.dist-info/licenses/LICENSE
maze_agent-1.0.2.dist-info/METADATA
maze_agent-1.0.2.dist-info/WHEEL
maze_agent-1.0.2.dist-info/entry_points.txt
maze_agent-1.0.2.dist-info/top_level.txt
maze_agent-1.0.2.dist-info/RECORD
