Metadata-Version: 2.4
Name: maze-agent
Version: 1.0.2
Summary: A Task-Level Distributed Agent Workflow Framework for building scalable, resource-efficient multi-agent systems
Author-email: Maze Development Team <your-email@example.com>
Maintainer-email: Maze Development Team <your-email@example.com>
License: MIT
Project-URL: Homepage, https://github.com/QinbinLi/Maze
Project-URL: Documentation, https://maze-doc-new.readthedocs.io/en/latest/
Project-URL: Repository, https://github.com/QinbinLi/Maze
Project-URL: Bug Tracker, https://github.com/QinbinLi/Maze/issues
Keywords: agent,workflow,distributed,multi-agent,task-scheduling,ray,langgraph,ai-agent,resource-management
Classifier: Development Status :: 4 - Beta
Classifier: Intended Audience :: Developers
Classifier: Intended Audience :: Science/Research
Classifier: License :: OSI Approved :: MIT License
Classifier: Operating System :: OS Independent
Classifier: Programming Language :: Python :: 3
Classifier: Programming Language :: Python :: 3.10
Classifier: Programming Language :: Python :: 3.11
Classifier: Programming Language :: Python :: 3.12
Classifier: Topic :: Scientific/Engineering :: Artificial Intelligence
Classifier: Topic :: Software Development :: Libraries :: Python Modules
Classifier: Topic :: System :: Distributed Computing
Requires-Python: >=3.10
License-File: LICENSE
Requires-Dist: fastapi==0.119.1
Requires-Dist: ray==2.50.1
Requires-Dist: uvicorn[standard]
Requires-Dist: zmq==0.0.0
Requires-Dist: networkx==3.4.2
Requires-Dist: websocket-client==1.9.0
Requires-Dist: cloudpickle==3.1.1
Requires-Dist: requests>=2.31.0
Requires-Dist: PyPDF2>=3.0.0
Requires-Dist: openpyxl>=3.1.0
Requires-Dist: python-docx>=0.8.11
Requires-Dist: mutagen>=1.46.0
Requires-Dist: Pillow>=9.0.0
Requires-Dist: opencv-python>=4.8.0
Provides-Extra: dev
Requires-Dist: pytest>=7.4.0; extra == "dev"
Requires-Dist: pytest-asyncio>=0.21.0; extra == "dev"
Requires-Dist: pytest-cov>=4.1.0; extra == "dev"
Dynamic: license-file
